{
  "id": "t10-08",
  "tier": 10,
  "number": 98,
  "name": "最終試験 収束",
  "briefing": "全ギミックを通した盤面読解を扱うステージです。操作を確定する前に、箱を押した後の退路まで確認してください。",
  "difficulty": 10,
  "mechanics": [
    "push",
    "switch",
    "oneWay",
    "warp",
    "ice"
  ],
  "map": [
    "#################",
    "#################",
    "#....##..#......#",
    "#...1#1I.#......#",
    "#....##..#P.....#",
    "#....#..<D.S.C..#",
    "#E...#...#..GC..#",
    "#################",
    "#################"
  ],
  "legend": {
    "1": {
      "kind": "warp",
      "channel": "alpha"
    },
    "S": {
      "kind": "switch",
      "channel": "alpha",
      "goal": true
    },
    "D": {
      "kind": "door",
      "channel": "alpha"
    }
  },
  "solution": "RRRRDDRLLRULLULLDLLLURULDDDLLL"
}
